README.rst
setup.py
bin/wagtaildemo
wagtail_simple_demo.egg-info/PKG-INFO
wagtail_simple_demo.egg-info/SOURCES.txt
wagtail_simple_demo.egg-info/dependency_links.txt
wagtail_simple_demo.egg-info/not-zip-safe
wagtail_simple_demo.egg-info/requires.txt
wagtail_simple_demo.egg-info/top_level.txt
wagtaildemo/__init__.py
wagtaildemo/content/__init__.py
wagtaildemo/core/__init__.py
wagtaildemo/core/urls.py
wagtaildemo/core/wsgi.py
wagtaildemo/home/__init__.py
wagtaildemo/management/__init__.py
wagtaildemo/management/commands/__init__.py
wagtaildemo/management/commands/demodata.py
wagtaildemo/settings/__init__.py
wagtaildemo/settings/base.py